file_remark/__init__.py
file_remark/__main__.py
file_remark/config.py
file_remark/main.py
file_remark/my_db.py
file_remark/tools.py
file_remark/user_exception.py
file_remark/data/__init__.py
file_remark/data/help.info
file_remark/module/__init__.py
file_remark/module/m_files.py
file_remark/sql/__init__.py
file_remark/sql/config.sql
file_remark/sql/config_data.sql
file_remark/sql/files.sql
file_remark/sql/v3.sql
file_remark_icexmoon-0.0.7.dist-info/LICENSE
file_remark_icexmoon-0.0.7.dist-info/METADATA
file_remark_icexmoon-0.0.7.dist-info/WHEEL
file_remark_icexmoon-0.0.7.dist-info/entry_points.txt
file_remark_icexmoon-0.0.7.dist-info/top_level.txt
file_remark_icexmoon-0.0.7.dist-info/RECORD
