Metadata-Version: 2.1
Name: file-remark-icexmoon
Version: 0.0.7
Summary: Add a remark for the file in the OS.
Home-page: https://github.com/icexmoon/file-remark
Author: icexmoon
Author-email: icexmoon@qq.com
License: UNKNOWN
Project-URL: Bug Tracker, https://github.com/icexmoon/file-remark/issues
Platform: UNKNOWN
Classifier: Programming Language :: Python :: 3
Classifier: License :: OSI Approved :: MIT License
Classifier: Operating System :: OS Independent
Requires-Python: >=3.6
License-File: LICENSE
Requires-Dist: requests
